main.py
calculator_wolfskullcave-1.0.1.dist-info/METADATA
calculator_wolfskullcave-1.0.1.dist-info/WHEEL
calculator_wolfskullcave-1.0.1.dist-info/entry_points.txt
calculator_wolfskullcave-1.0.1.dist-info/top_level.txt
calculator_wolfskullcave-1.0.1.dist-info/RECORD
