Metadata-Version: 2.4
Name: calculator-wolfskullcave
Version: 1.0.1
Summary: A simple command-line calculator
Requires-Python: >=3.12
Requires-Dist: sympy>=1.13.3
Requires-Dist: typer>=0.15.2
